people_analytics_itsm_sdk/__init__.py
people_analytics_itsm_sdk/exceptions.py
people_analytics_itsm_sdk/sdk/__init__.py
people_analytics_itsm_sdk/sdk/servicenow/__init__.py
people_analytics_itsm_sdk/sdk/servicenow/attachments/__init__.py
people_analytics_itsm_sdk/sdk/servicenow/attachments/client.py
people_analytics_itsm_sdk/sdk/servicenow/attachments/exceptions.py
people_analytics_itsm_sdk/sdk/servicenow/helpers/__init__.py
people_analytics_itsm_sdk/sdk/servicenow/helpers/client.py
people_analytics_itsm_sdk/sdk/servicenow/helpers/query_builder.py
people_analytics_itsm_sdk/sdk/servicenow/table/__init__.py
people_analytics_itsm_sdk/sdk/servicenow/table/client.py
people_analytics_itsm_sdk/sdk/servicenow/table/exceptions.py
people_analytics_itsm_sdk/settings.py
people_analytics_itsm_sdk-0.0.17.dist-info/WHEEL
people_analytics_itsm_sdk-0.0.17.dist-info/METADATA
people_analytics_itsm_sdk-0.0.17.dist-info/RECORD
