Metadata-Version: 2.1
Name: people-analytics-itsm-sdk
Version: 0.0.17
Summary: People analytics itsm sdk is used to facilitate integrations and also code reuse
Author: Stone People Analytics
Author-email: systems-techpeople@stone.com.br
Requires-Python: >=3.9,<4.0
Classifier: Programming Language :: Python :: 3
Classifier: Programming Language :: Python :: 3.10
Classifier: Programming Language :: Python :: 3.9
Requires-Dist: requests (>=2.27.1,<3.0.0)
